StringFormat/Formatter.py
StringFormat/__init__.py
robotframework-stringformat/Formatter.py
robotframework-stringformat/__init__.py
robotframework_stringformat-0.1.8.dist-info/METADATA
robotframework_stringformat-0.1.8.dist-info/RECORD
robotframework_stringformat-0.1.8.dist-info/WHEEL
robotframework_stringformat-0.1.8.dist-info/top_level.txt
